env_loader/__init__.py
env_loader/consts.py
env_loader/env_file.py
env_loader/main.py
env_loader/parser.py
python_env_loader-0.0.2.dist-info/LICENSE
python_env_loader-0.0.2.dist-info/METADATA
python_env_loader-0.0.2.dist-info/WHEEL
python_env_loader-0.0.2.dist-info/top_level.txt
python_env_loader-0.0.2.dist-info/RECORD
