Metadata-Version: 2.1
Name: python-env-loader
Version: 0.0.2
Summary: Reads the variables from .env files and adds them to environment, also automatically guesses and parses to correct types in Python. 
Home-page: https://github.com/rafaljusiak/python-env-loader
Author: Rafał Jusiak
Author-email: kontakt@rafaljusiak.pl
License: UNKNOWN
Platform: UNKNOWN
Classifier: Programming Language :: Python :: 3
Classifier: License :: OSI Approved :: MIT License
Classifier: Operating System :: OS Independent
Requires-Python: >=3.6
